tfjackal/__init__.py
tfjackal-0.0.1.dist-info/LICENSE
tfjackal-0.0.1.dist-info/METADATA
tfjackal-0.0.1.dist-info/WHEEL
tfjackal-0.0.1.dist-info/top_level.txt
tfjackal-0.0.1.dist-info/RECORD
