Metadata-Version: 2.1
Name: tfjackal
Version: 0.0.1
Summary: A library for Tensorflow model evaluation
Author-email: James Calo <jamesafcalo@gmail.com>
License: GNU GENERAL PUBLIC LICENSE
Classifier: Development Status :: 1 - Planning
Classifier: Intended Audience :: Science/Research
Classifier: License :: OSI Approved :: GNU General Public License v3 (GPLv3)
Classifier: Programming Language :: Python :: 3.11
Classifier: Topic :: Scientific/Engineering :: Artificial Intelligence
Requires-Python: >=3.11
License-File: LICENSE
Requires-Dist: numpy
Requires-Dist: tensorflow
Requires-Dist: matplotlib
